macos_pkg_builder/__init__.py
macos_pkg_builder/core.py
macos_pkg_builder/distribution_pkg.py
macos_pkg_builder/flat_pkg.py
macos_pkg_builder/utilities/__init__.py
macos_pkg_builder/utilities/copy.py
macos_pkg_builder/utilities/signing.py
macos_pkg_builder/utilities/subprocess_wrapper.py
macos_pkg_builder-2.2.0.dist-info/LICENSE.txt
macos_pkg_builder-2.2.0.dist-info/METADATA
macos_pkg_builder-2.2.0.dist-info/WHEEL
macos_pkg_builder-2.2.0.dist-info/top_level.txt
macos_pkg_builder-2.2.0.dist-info/RECORD
