Metadata-Version: 2.1
Name: macos_pkg_builder
Version: 2.2.0
Summary: macOS Package Builder Library, wrapping Apple's 'pkgbuild' and 'productbuild' utilities.
Home-page: https://github.com/ripeda/macOS-Pkg-Builder
Author: RIPEDA Consulting
Author-email: info@ripeda.com
Requires-Python: >=3.6
License-File: LICENSE.txt
Requires-Dist: markdown
